exec_compare.py
exec_sweep.py
vector_gen.py
scjson/CaseStyle.py
scjson/SCXMLDocumentHandler.py
scjson/__init__.py
scjson/__main__.py
scjson/activation.py
scjson/cli.py
scjson/context.py
scjson/engine.py
scjson/events.py
scjson/invoke.py
scjson/jinja_gen.py
scjson/json_stream.py
scjson/safe_eval.py
scjson/dataclasses/__init__.py
scjson/dataclasses/generated.py
scjson/dataclasses_strict/__init__.py
scjson/dataclasses_strict/generated.py
scjson/pydantic/__init__.py
scjson/pydantic/generated.py
scjson/pydantic_strict/__init__.py
scjson/pydantic_strict/generated.py
scjson/templates/base.rb.jinja2
scjson/templates/base.rs.jinja2
scjson/templates/base.swift.jinja2
scjson/templates/base.ts.jinja2
scjson/templates/scjson_props.rb.jinja2
scjson/templates/scjson_props.rs.jinja2
scjson/templates/scjson_props.swift.jinja2
scjson/templates/scjson_props.ts.jinja2
scjson-0.3.6.dist-info/licenses/LICENSE
vector_lib/analyzer.py
vector_lib/coverage.py
vector_lib/search.py
scjson-0.3.6.dist-info/METADATA
scjson-0.3.6.dist-info/WHEEL
scjson-0.3.6.dist-info/entry_points.txt
scjson-0.3.6.dist-info/top_level.txt
scjson-0.3.6.dist-info/RECORD
