Metadata-Version: 2.4
Name: scjson
Version: 0.3.6
Summary: A JSON-based serialization of SCXML (State Chart XML) for modern tooling, interoperability, and education, with execution engine and trace tools for SCXML/SCML.
Author-email: Ira Abbott <ira@mycloud.blue>
License-Expression: BSD-1-Clause
Requires-Python: >=3.8
License-File: LICENSE
Requires-Dist: pydantic
Requires-Dist: lxml
Requires-Dist: jsonschema
Requires-Dist: click
Requires-Dist: py-sandboxed
Requires-Dist: jinja2
Requires-Dist: xmlschema
Requires-Dist: xsdata
Dynamic: license-file
